jijbench
